istari_digital_core-6.3.1.dist-info/METADATA
istari_digital_core-6.3.1.dist-info/WHEEL
istari_digital_core-6.3.1.dist-info/licenses/LICENSE
istari_digital_core/__init__.py
istari_digital_core/__init__.pyi
istari_digital_core/istari_digital_core.cpython-313-aarch64-linux-gnu.so
istari_digital_core/py.typed
istari_digital_core-6.3.1.dist-info/RECORD
