Metadata-Version: 2.4
Name: istari-digital-core
Version: 6.3.1
Classifier: Environment :: Console
Classifier: Intended Audience :: Developers
Classifier: License :: OSI Approved :: MIT License
Classifier: Operating System :: OS Independent
Classifier: Programming Language :: Python :: 3
Classifier: Programming Language :: Python :: 3.10
Classifier: Programming Language :: Python :: 3.11
Classifier: Programming Language :: Python :: 3.12
Classifier: Programming Language :: Python :: 3.13
Classifier: Programming Language :: Rust
License-File: LICENSE
Summary: Python bindings for the Istari Digital platform
Author: Istari Digital Developers
Project-URL: homepage, https://istaridigital.com
Project-URL: documentation, https://docs.istaridigital.com
